License.txt
setup.py
eeg_library/__init__.py
eeg_library/test1.py
eeg_pipline.egg-info/PKG-INFO
eeg_pipline.egg-info/SOURCES.txt
eeg_pipline.egg-info/dependency_links.txt
eeg_pipline.egg-info/not-zip-safe
eeg_pipline.egg-info/top_level.txt